[
  {
    "text": "review",
    "done": false,
    "time_spent": 66.7576014995575,
    "history": [
      {
        "start": 1774918445,
        "stop": 1774918446
      },
      {
        "start": 1774918491,
        "stop": 1774918497,
        "memo": "test1"
      },
      {
        "start": 1774918499,
        "stop": 1774918499
      },
      {
        "start": 1774918501,
        "stop": 1774918559
      }
    ],
    "is_running": false
  },
  {
    "text": "Layout Check",
    "done": false,
    "time_spent": 0,
    "history": [],
    "is_running": false
  },
  {
    "text": "Design Verification",
    "done": false,
    "time_spent": 0,
    "history": [],
    "is_running": false
  }
]